{
  "name": "Satish",
  "email": "satish.jnext@gmail.com",
  "base_url": "https://staging.smartb.au.sydney.digiground.com.au/",
  "raceName": "Gotba Plate Ht1 9",
  "trackName": "The Meadows",
  "raceAlert": {
    "mailStatus": "sent",
    "id": 825,
    "raceId": 136178,
    "status": "sent",
    "userId": 6,
    "type": "race",
    "bookMaker": [
      { "type": "oddWin", "bookkeepersId": 3 },
      { "type": "oddPlace", "bookkeepersId": 3 },
      { "type": "oddWin", "bookkeepersId": 4 },
      { "type": "oddPlace", "bookkeepersId": 4 }
    ],
    "triggerPrice": "any",
    "triggerPriceType": null,
    "updatedAt": "2025-05-07T11:45:54.133Z",
    "createdAt": "2025-05-07T11:45:54.133Z"
  },
  "raceDetails": {
    "race": {
      "id": 136178,
      "eventId": 11769,
      "sportId": 3,
      "raceName": "Gotba Plate Ht1",
      "description": "Gotba Plate Ht1",
      "distance": 74,
      "startDate": "2025-05-07T11:48:00.000Z",
      "startTimeDate": "2025-05-07T11:48:00.000Z",
      "comment": "GALENTO (6) looks close to another win after hitting the frame in a 1.3 lengths second (30.15) in a Mix 6/7 at this track. Top chance in this line up. WITHOUT A TRACE (3) will take beating coming off a decent 29.46 win at Sandown over 515m. This tougher but expected to be in the finish. DUBROW (1) shapes well for this after winning last start over the 425m at Bendigo in a dominant 23.75. In form and looks a leading player again. ASTON BARTON (4) can play a role in the finish without surprising.",
      "weather": 4,
      "raceNumber": 9,
      "apiProvicerId": 2,
      "raceClass": "mixed 6/7 heat",
      "status": "Open",
      "trackCondition": "Good",
      "trackId": 195,
      "prizeMoney": 0,
      "action": 0,
      "resultDisplay": null,
      "rail": "",
      "silk_url": "https://www.neds.com.au/images/sprites/greyhound-silks-standard.png",
      "actual_start": "2025-05-07T11:48:00.000Z",
      "createdAt": "2025-05-05T04:32:26.000Z",
      "updatedAt": "2025-05-07T06:33:03.000Z",
      "Weather": {
        "id": 4,
        "weatherType": "Fine",
        "createdAt": "2024-10-24T07:37:04.000Z",
        "updatedAt": "2024-10-24T07:37:04.000Z"
      },
      "Distance": {
        "id": 74,
        "name": "525",
        "variation": null,
        "createdAt": "2024-10-24T07:34:46.000Z",
        "updatedAt": "2024-10-24T07:34:46.000Z"
      },
      "track": {
        "id": 195,
        "name": "The Meadows",
        "variation": null,
        "createdBy": 1,
        "updatedBy": 1,
        "stateId": null,
        "countryId": 13,
        "cityId": null,
        "sportId": 3,
        "createdAt": "2022-10-20T22:38:05.000Z",
        "updatedAt": "2022-10-20T22:38:05.000Z",
        "Country": {
          "id": 13,
          "country": "Australia",
          "countryCode": "AUS",
          "country_flag": "uploads/1733872976149.png",
          "variation": "AUS",
          "updateRequired": false,
          "createdAt": "1970-01-19T16:21:06.000Z",
          "updatedAt": "2024-12-10T23:22:56.000Z"
        },
        "City": null,
        "State": null
      }
    },
    "runners": [
      {
        "id": 1059263,
        "particiantIdetifier": null,
        "particiantId": 662181,
        "barrierNumber": 1,
        "runnerNumber": 1,
        "isScratched": "0",
        "scratchTime": null,
        "runnerComments": null,
        "createdBy": null,
        "updatedBy": null,
        "JockeyWeight": "0",
        "prizeMoney": null,
        "runnerProviderId": "20129e81-b5fa-48fb-80c4-06992360916f",
        "raceId": 136178,
        "selectionId": null,
        "createdAt": "2025-05-05T04:32:26.000Z",
        "updatedAt": "2025-05-07T06:33:03.000Z",
        "TrainerId": 5627,
        "JockeyId": null,
        "animal": {
          "id": 662181,
          "name": "Dubrow",
          "variation": null,
          "runnerNumber": null,
          "age": null,
          "genderId": null,
          "colourId": null,
          "silkColour": null,
          "animalTypeId": 1,
          "createdAt": "2025-01-15T08:57:41.000Z",
          "updatedAt": "2025-01-15T08:57:41.000Z"
        },
        "Jockey": null,
        "Trainer": {
          "id": 5627,
          "name": "John Barbara",
          "weight": null,
          "image": null,
          "createdAt": "2024-10-24T18:13:52.000Z",
          "updatedAt": "2024-10-24T18:13:52.000Z"
        },
        "bookmakerMarkets": [
          {
            "bookKeeperId": 3,
            "bookmaker": "Neds",
            "type": "oddWin",
            "key": null,
            "oddType": "Fixed W",
            "odd": 3,
            "logo_bg": "#ff7800",
            "small_logo": "uploads/1717570898864.png"
          },
          {
            "bookKeeperId": 3,
            "bookmaker": "Neds",
            "type": "oddPlace",
            "key": null,
            "oddType": "Fixed P",
            "odd": 1.55,
            "logo_bg": "#ff7800",
            "small_logo": "uploads/1717570898864.png"
          },
          {
            "bookKeeperId": 4,
            "bookmaker": "Ladbrokes",
            "type": "oddWin",
            "key": null,
            "oddType": "Fixed W",
            "odd": 3,
            "logo_bg": "#e12826",
            "small_logo": "uploads/1717571245067.png"
          },
          {
            "bookKeeperId": 4,
            "bookmaker": "Ladbrokes",
            "type": "oddPlace",
            "key": null,
            "oddType": "Fixed P",
            "odd": 1.55,
            "logo_bg": "#e12826",
            "small_logo": "uploads/1717571245067.png"
          }
        ]
      },
      {
        "id": 1059264,
        "particiantIdetifier": null,
        "particiantId": 670453,
        "barrierNumber": 2,
        "runnerNumber": 2,
        "isScratched": "0",
        "scratchTime": null,
        "runnerComments": null,
        "createdBy": null,
        "updatedBy": null,
        "JockeyWeight": "0",
        "prizeMoney": null,
        "runnerProviderId": "607e420d-c373-4b1d-ac40-8429356e54aa",
        "raceId": 136178,
        "selectionId": null,
        "createdAt": "2025-05-05T04:32:27.000Z",
        "updatedAt": "2025-05-07T06:33:03.000Z",
        "TrainerId": 6920,
        "JockeyId": null,
        "animal": {
          "id": 670453,
          "name": "Strike It Mike",
          "variation": null,
          "runnerNumber": null,
          "age": null,
          "genderId": null,
          "colourId": null,
          "silkColour": null,
          "animalTypeId": 1,
          "createdAt": "2025-01-31T16:36:26.000Z",
          "updatedAt": "2025-01-31T16:36:26.000Z"
        },
        "Jockey": null,
        "Trainer": {
          "id": 6920,
          "name": "Shona Crawford",
          "weight": null,
          "image": null,
          "createdAt": "2024-10-24T08:20:54.000Z",
          "updatedAt": "2024-10-24T08:20:54.000Z"
        },
        "bookmakerMarkets": [
          {
            "bookKeeperId": 3,
            "bookmaker": "Neds",
            "type": "oddWin",
            "key": null,
            "oddType": "Fixed W",
            "odd": 41,
            "logo_bg": "#ff7800",
            "small_logo": "uploads/1717570898864.png"
          },
          {
            "bookKeeperId": 3,
            "bookmaker": "Neds",
            "type": "oddPlace",
            "key": null,
            "oddType": "Fixed P",
            "odd": 9.5,
            "logo_bg": "#ff7800",
            "small_logo": "uploads/1717570898864.png"
          },
          {
            "bookKeeperId": 4,
            "bookmaker": "Ladbrokes",
            "type": "oddWin",
            "key": null,
            "oddType": "Fixed W",
            "odd": 41,
            "logo_bg": "#e12826",
            "small_logo": "uploads/1717571245067.png"
          },
          {
            "bookKeeperId": 4,
            "bookmaker": "Ladbrokes",
            "type": "oddPlace",
            "key": null,
            "oddType": "Fixed P",
            "odd": 9.5,
            "logo_bg": "#e12826",
            "small_logo": "uploads/1717571245067.png"
          }
        ]
      },
      {
        "id": 1059265,
        "particiantIdetifier": null,
        "particiantId": 505002,
        "barrierNumber": 3,
        "runnerNumber": 3,
        "isScratched": "0",
        "scratchTime": null,
        "runnerComments": null,
        "createdBy": null,
        "updatedBy": null,
        "JockeyWeight": "0",
        "prizeMoney": null,
        "runnerProviderId": "cbacc78d-3406-4b0f-ba10-59ec1c8f2d14",
        "raceId": 136178,
        "selectionId": null,
        "createdAt": "2025-05-05T04:32:27.000Z",
        "updatedAt": "2025-05-07T06:33:03.000Z",
        "TrainerId": 5239,
        "JockeyId": null,
        "animal": {
          "id": 505002,
          "name": "Without A Trace",
          "variation": null,
          "runnerNumber": null,
          "age": null,
          "genderId": null,
          "colourId": null,
          "silkColour": null,
          "animalTypeId": 1,
          "createdAt": "2024-05-15T22:55:36.000Z",
          "updatedAt": "2024-05-15T22:55:36.000Z"
        },
        "Jockey": null,
        "Trainer": {
          "id": 5239,
          "name": "Peter Presutto",
          "weight": null,
          "image": null,
          "createdAt": "2024-10-24T18:10:58.000Z",
          "updatedAt": "2024-10-24T18:10:58.000Z"
        },
        "bookmakerMarkets": [
          {
            "bookKeeperId": 3,
            "bookmaker": "Neds",
            "type": "oddWin",
            "key": null,
            "oddType": "Fixed W",
            "odd": 2.5,
            "logo_bg": "#ff7800",
            "small_logo": "uploads/1717570898864.png"
          },
          {
            "bookKeeperId": 3,
            "bookmaker": "Neds",
            "type": "oddPlace",
            "key": null,
            "oddType": "Fixed P",
            "odd": 1.4,
            "logo_bg": "#ff7800",
            "small_logo": "uploads/1717570898864.png"
          },
          {
            "bookKeeperId": 4,
            "bookmaker": "Ladbrokes",
            "type": "oddWin",
            "key": null,
            "oddType": "Fixed W",
            "odd": 2.5,
            "logo_bg": "#e12826",
            "small_logo": "uploads/1717571245067.png"
          },
          {
            "bookKeeperId": 4,
            "bookmaker": "Ladbrokes",
            "type": "oddPlace",
            "key": null,
            "oddType": "Fixed P",
            "odd": 1.4,
            "logo_bg": "#e12826",
            "small_logo": "uploads/1717571245067.png"
          }
        ]
      },
      {
        "id": 1059266,
        "particiantIdetifier": null,
        "particiantId": 657220,
        "barrierNumber": 4,
        "runnerNumber": 4,
        "isScratched": "0",
        "scratchTime": null,
        "runnerComments": null,
        "createdBy": null,
        "updatedBy": null,
        "JockeyWeight": "0",
        "prizeMoney": null,
        "runnerProviderId": "50ee8257-70e8-49ca-9bea-9b929f238c44",
        "raceId": 136178,
        "selectionId": null,
        "createdAt": "2025-05-05T04:32:28.000Z",
        "updatedAt": "2025-05-07T06:33:03.000Z",
        "TrainerId": 5726,
        "JockeyId": null,
        "animal": {
          "id": 657220,
          "name": "Aston Barton",
          "variation": null,
          "runnerNumber": null,
          "age": null,
          "genderId": null,
          "colourId": null,
          "silkColour": null,
          "animalTypeId": 1,
          "createdAt": "2025-01-09T04:12:52.000Z",
          "updatedAt": "2025-01-09T04:12:52.000Z"
        },
        "Jockey": null,
        "Trainer": {
          "id": 5726,
          "name": "Benjamin Magri",
          "weight": null,
          "image": null,
          "createdAt": "2024-10-24T18:14:41.000Z",
          "updatedAt": "2024-10-24T18:14:41.000Z"
        },
        "bookmakerMarkets": [
          {
            "bookKeeperId": 3,
            "bookmaker": "Neds",
            "type": "oddWin",
            "key": null,
            "oddType": "Fixed W",
            "odd": 11,
            "logo_bg": "#ff7800",
            "small_logo": "uploads/1717570898864.png"
          },
          {
            "bookKeeperId": 3,
            "bookmaker": "Neds",
            "type": "oddPlace",
            "key": null,
            "oddType": "Fixed P",
            "odd": 3.7,
            "logo_bg": "#ff7800",
            "small_logo": "uploads/1717570898864.png"
          },
          {
            "bookKeeperId": 4,
            "bookmaker": "Ladbrokes",
            "type": "oddWin",
            "key": null,
            "oddType": "Fixed W",
            "odd": 11,
            "logo_bg": "#e12826",
            "small_logo": "uploads/1717571245067.png"
          },
          {
            "bookKeeperId": 4,
            "bookmaker": "Ladbrokes",
            "type": "oddPlace",
            "key": null,
            "oddType": "Fixed P",
            "odd": 3.7,
            "logo_bg": "#e12826",
            "small_logo": "uploads/1717571245067.png"
          }
        ]
      },
      {
        "id": 1059267,
        "particiantIdetifier": null,
        "particiantId": 480005,
        "barrierNumber": 5,
        "runnerNumber": 5,
        "isScratched": 1,
        "scratchTime": "2025-05-05T04:09:27.000Z",
        "runnerComments": null,
        "createdBy": null,
        "updatedBy": null,
        "JockeyWeight": "0",
        "prizeMoney": null,
        "runnerProviderId": "df05fde8-fc4c-4b2e-8646-d91b52f961f2",
        "raceId": 136178,
        "selectionId": null,
        "createdAt": "2025-05-05T04:32:28.000Z",
        "updatedAt": "2025-05-07T06:33:03.000Z",
        "TrainerId": 27935,
        "JockeyId": null,
        "animal": {
          "id": 480005,
          "name": "Vacant Box",
          "variation": null,
          "runnerNumber": null,
          "age": null,
          "genderId": null,
          "colourId": null,
          "silkColour": null,
          "animalTypeId": 1,
          "createdAt": "2024-05-14T15:09:51.000Z",
          "updatedAt": "2024-05-14T15:09:51.000Z"
        },
        "Jockey": null,
        "Trainer": {
          "id": 27935,
          "name": "No Trainer",
          "weight": null,
          "image": null,
          "createdAt": "2025-02-12T13:23:28.000Z",
          "updatedAt": "2025-02-12T13:23:28.000Z"
        },
        "bookmakerMarkets": [
          {
            "bookKeeperId": 3,
            "bookmaker": "Neds",
            "type": "oddWin",
            "key": null,
            "oddType": "Fixed W",
            "odd": 0,
            "logo_bg": "#ff7800",
            "small_logo": "uploads/1717570898864.png"
          },
          {
            "bookKeeperId": 3,
            "bookmaker": "Neds",
            "type": "oddPlace",
            "key": null,
            "oddType": "Fixed P",
            "odd": 0,
            "logo_bg": "#ff7800",
            "small_logo": "uploads/1717570898864.png"
          },
          {
            "bookKeeperId": 4,
            "bookmaker": "Ladbrokes",
            "type": "oddWin",
            "key": null,
            "oddType": "Fixed W",
            "odd": 0,
            "logo_bg": "#e12826",
            "small_logo": "uploads/1717571245067.png"
          },
          {
            "bookKeeperId": 4,
            "bookmaker": "Ladbrokes",
            "type": "oddPlace",
            "key": null,
            "oddType": "Fixed P",
            "odd": 0,
            "logo_bg": "#e12826",
            "small_logo": "uploads/1717571245067.png"
          }
        ]
      },
      {
        "id": 1059268,
        "particiantIdetifier": null,
        "particiantId": 681377,
        "barrierNumber": 6,
        "runnerNumber": 6,
        "isScratched": "0",
        "scratchTime": null,
        "runnerComments": null,
        "createdBy": null,
        "updatedBy": null,
        "JockeyWeight": "0",
        "prizeMoney": null,
        "runnerProviderId": "e60c6e0d-c754-46c5-8dcd-5a271f438a85",
        "raceId": 136178,
        "selectionId": null,
        "createdAt": "2025-05-05T04:32:28.000Z",
        "updatedAt": "2025-05-07T06:33:03.000Z",
        "TrainerId": 8964,
        "JockeyId": null,
        "animal": {
          "id": 681377,
          "name": "Galento",
          "variation": null,
          "runnerNumber": null,
          "age": null,
          "genderId": null,
          "colourId": null,
          "silkColour": null,
          "animalTypeId": 1,
          "createdAt": "2025-03-07T01:40:56.000Z",
          "updatedAt": "2025-03-07T01:40:56.000Z"
        },
        "Jockey": null,
        "Trainer": {
          "id": 8964,
          "name": "Paul Galea",
          "weight": null,
          "image": null,
          "createdAt": "2024-10-25T01:08:41.000Z",
          "updatedAt": "2024-10-25T01:08:41.000Z"
        },
        "bookmakerMarkets": [
          {
            "bookKeeperId": 3,
            "bookmaker": "Neds",
            "type": "oddWin",
            "key": null,
            "oddType": "Fixed W",
            "odd": 2.9,
            "logo_bg": "#ff7800",
            "small_logo": "uploads/1717570898864.png"
          },
          {
            "bookKeeperId": 3,
            "bookmaker": "Neds",
            "type": "oddPlace",
            "key": null,
            "oddType": "Fixed P",
            "odd": 1.55,
            "logo_bg": "#ff7800",
            "small_logo": "uploads/1717570898864.png"
          },
          {
            "bookKeeperId": 4,
            "bookmaker": "Ladbrokes",
            "type": "oddWin",
            "key": null,
            "oddType": "Fixed W",
            "odd": 2.9,
            "logo_bg": "#e12826",
            "small_logo": "uploads/1717571245067.png"
          },
          {
            "bookKeeperId": 4,
            "bookmaker": "Ladbrokes",
            "type": "oddPlace",
            "key": null,
            "oddType": "Fixed P",
            "odd": 1.55,
            "logo_bg": "#e12826",
            "small_logo": "uploads/1717571245067.png"
          }
        ]
      },
      {
        "id": 1059269,
        "particiantIdetifier": null,
        "particiantId": 593257,
        "barrierNumber": 7,
        "runnerNumber": 7,
        "isScratched": "0",
        "scratchTime": null,
        "runnerComments": null,
        "createdBy": null,
        "updatedBy": null,
        "JockeyWeight": "0",
        "prizeMoney": null,
        "runnerProviderId": "1d6bef18-fa46-403e-b4b7-e92f2029573b",
        "raceId": 136178,
        "selectionId": null,
        "createdAt": "2025-05-05T04:32:28.000Z",
        "updatedAt": "2025-05-07T06:33:03.000Z",
        "TrainerId": 2490,
        "JockeyId": null,
        "animal": {
          "id": 593257,
          "name": "Crown Arya",
          "variation": null,
          "runnerNumber": null,
          "age": null,
          "genderId": null,
          "colourId": null,
          "silkColour": null,
          "animalTypeId": 1,
          "createdAt": "2024-10-24T08:19:20.000Z",
          "updatedAt": "2024-10-24T08:19:20.000Z"
        },
        "Jockey": null,
        "Trainer": {
          "id": 2490,
          "name": "Tammy Kennedy Harris",
          "weight": null,
          "image": null,
          "createdAt": "2024-10-24T07:43:08.000Z",
          "updatedAt": "2024-10-24T07:43:08.000Z"
        },
        "bookmakerMarkets": [
          {
            "bookKeeperId": 3,
            "bookmaker": "Neds",
            "type": "oddWin",
            "key": null,
            "oddType": "Fixed W",
            "odd": 81,
            "logo_bg": "#ff7800",
            "small_logo": "uploads/1717570898864.png"
          },
          {
            "bookKeeperId": 3,
            "bookmaker": "Neds",
            "type": "oddPlace",
            "key": null,
            "oddType": "Fixed P",
            "odd": 16,
            "logo_bg": "#ff7800",
            "small_logo": "uploads/1717570898864.png"
          },
          {
            "bookKeeperId": 4,
            "bookmaker": "Ladbrokes",
            "type": "oddWin",
            "key": null,
            "oddType": "Fixed W",
            "odd": 81,
            "logo_bg": "#e12826",
            "small_logo": "uploads/1717571245067.png"
          },
          {
            "bookKeeperId": 4,
            "bookmaker": "Ladbrokes",
            "type": "oddPlace",
            "key": null,
            "oddType": "Fixed P",
            "odd": 16,
            "logo_bg": "#e12826",
            "small_logo": "uploads/1717571245067.png"
          }
        ]
      },
      {
        "id": 1059270,
        "particiantIdetifier": null,
        "particiantId": 671166,
        "barrierNumber": 8,
        "runnerNumber": 8,
        "isScratched": "0",
        "scratchTime": null,
        "runnerComments": null,
        "createdBy": null,
        "updatedBy": null,
        "JockeyWeight": "0",
        "prizeMoney": null,
        "runnerProviderId": "b2a48630-0ccd-4acf-a482-3d7e34596370",
        "raceId": 136178,
        "selectionId": null,
        "createdAt": "2025-05-05T04:32:28.000Z",
        "updatedAt": "2025-05-07T06:33:03.000Z",
        "TrainerId": 2462,
        "JockeyId": null,
        "animal": {
          "id": 671166,
          "name": "Westar Leo",
          "variation": null,
          "runnerNumber": null,
          "age": null,
          "genderId": null,
          "colourId": null,
          "silkColour": null,
          "animalTypeId": 1,
          "createdAt": "2025-02-03T08:34:44.000Z",
          "updatedAt": "2025-02-03T08:34:44.000Z"
        },
        "Jockey": null,
        "Trainer": {
          "id": 2462,
          "name": "Jeffrey Britton",
          "weight": null,
          "image": null,
          "createdAt": "2024-10-24T07:43:02.000Z",
          "updatedAt": "2024-10-24T07:43:02.000Z"
        },
        "bookmakerMarkets": [
          {
            "bookKeeperId": 3,
            "bookmaker": "Neds",
            "type": "oddWin",
            "key": null,
            "oddType": "Fixed W",
            "odd": 46,
            "logo_bg": "#ff7800",
            "small_logo": "uploads/1717570898864.png"
          },
          {
            "bookKeeperId": 3,
            "bookmaker": "Neds",
            "type": "oddPlace",
            "key": null,
            "oddType": "Fixed P",
            "odd": 10,
            "logo_bg": "#ff7800",
            "small_logo": "uploads/1717570898864.png"
          },
          {
            "bookKeeperId": 4,
            "bookmaker": "Ladbrokes",
            "type": "oddWin",
            "key": null,
            "oddType": "Fixed W",
            "odd": 46,
            "logo_bg": "#e12826",
            "small_logo": "uploads/1717571245067.png"
          },
          {
            "bookKeeperId": 4,
            "bookmaker": "Ladbrokes",
            "type": "oddPlace",
            "key": null,
            "oddType": "Fixed P",
            "odd": 10,
            "logo_bg": "#e12826",
            "small_logo": "uploads/1717571245067.png"
          }
        ]
      }
    ]
  },
  "silk_url": "https://www.neds.com.au/images/sprites/greyhound-silks-standard.png"
}
